LICENSE
MANIFEST.in
README.rst
pavement.py
requirements-dev.txt
requirements.txt
setup.py
tox.ini
docs/Makefile
docs/make.bat
docs/source/README
docs/source/conf.py
docs/source/index.rst
docs/source/_static/.gitkeep
probcount/__init__.py
probcount/main.py
probcount/metadata.py
probcount/probcounterlib.py
probcount.egg-info/PKG-INFO
probcount.egg-info/SOURCES.txt
probcount.egg-info/dependency_links.txt
probcount.egg-info/entry_points.txt
probcount.egg-info/not-zip-safe
probcount.egg-info/top_level.txt
tests/test_usage.py